bake_o_matic.py
setup.py
bake_o_matic.egg-info/PKG-INFO
bake_o_matic.egg-info/SOURCES.txt
bake_o_matic.egg-info/dependency_links.txt
bake_o_matic.egg-info/top_level.txt