Metadata-Version: 1.0
Name: bake-o-matic
Version: 0.1
Summary: baker boilerplate reduction
Home-page: UNKNOWN
Author: tengu
Author-email: karasuyamatengu@gmail.com
License: LGPL
Platform: UNKNOWN
